aiocrwaler/__init__.py
aiocrwaler/core/__init__.py
aiocrwaler/core/stream_core.py
aiocrwaler/stream/__init__.py
aiocrwaler/stream/elasticsearch.py
aiocrwaler/stream/file.py
aiocrwaler/stream/mongo.py
aiocrwaler/stream/rabbit.py
aiocrwaler-0.1.0.dist-info/WHEEL
aiocrwaler-0.1.0.dist-info/METADATA
aiocrwaler-0.1.0.dist-info/RECORD
